aaargs/__init__.py
aaargs-0.1.3.dist-info/LICENSE
aaargs-0.1.3.dist-info/WHEEL
aaargs-0.1.3.dist-info/METADATA
aaargs-0.1.3.dist-info/RECORD
