Metadata-Version: 2.1
Name: aaargs
Version: 0.1.3
Summary: attribute autocompletion and argument parsing
License: Apache-2.0
Keywords: argparse,dataclass,zninit
Author: zincwarecode
Author-email: zincwarecode@gmail.com
Requires-Python: >=3.8,<4.0
Classifier: License :: OSI Approved :: Apache Software License
Classifier: Programming Language :: Python :: 3
Classifier: Programming Language :: Python :: 3.8
Classifier: Programming Language :: Python :: 3.9
Classifier: Programming Language :: Python :: 3.10
Classifier: Programming Language :: Python :: 3.11
Requires-Dist: zninit (>=0.1.2,<0.2.0)
Project-URL: repository, https://github.com/zincware/aaargs
